migration/__init__.py
migration/errors.py
migration/merge_template.json
migration/migrate_mysql.py
migration/migration_table.sql
py_migration_Orinnass-2.1.2.dist-info/METADATA
py_migration_Orinnass-2.1.2.dist-info/WHEEL
py_migration_Orinnass-2.1.2.dist-info/top_level.txt
py_migration_Orinnass-2.1.2.dist-info/RECORD
